{
    "10000002": {
        "iconName": "UI_AvatarIcon_Ayaka",
        "costumes": {}
    },
    "10000003": {
        "iconName": "UI_AvatarIcon_Qin",
        "costumes": {
            "200301": {
                "iconName": "UI_AvatarIcon_QinCostumeSea"
            },
            "200302": {
                "iconName": "UI_AvatarIcon_QinCostumeWic"
            }
        }
    },
    "10000005": {
        "iconName": "UI_AvatarIcon_PlayerBoy",
        "costumes": {}
    },
    "10000006": {
        "iconName": "UI_AvatarIcon_Lisa",
        "costumes": {}
    },
    "10000007": {
        "iconName": "UI_AvatarIcon_PlayerGirl",
        "costumes": {}
    },
    "10000014": {
        "iconName": "UI_AvatarIcon_Barbara",
        "costumes": {
            "201401": {
                "iconName": "UI_AvatarIcon_BarbaraCostumeSummertime"
            }
        }
    },
    "10000015": {
        "iconName": "UI_AvatarIcon_Kaeya",
        "costumes": {}
    },
    "10000016": {
        "iconName": "UI_AvatarIcon_Diluc",
        "costumes": {}
    },
    "10000020": {
        "iconName": "UI_AvatarIcon_Razor",
        "costumes": {}
    },
    "10000021": {
        "iconName": "UI_AvatarIcon_Ambor",
        "costumes": {
            "202101": {
                "iconName": "UI_AvatarIcon_AmborCostumeWic"
            }
        }
    },
    "10000022": {
        "iconName": "UI_AvatarIcon_Venti",
        "costumes": {}
    },
    "10000023": {
        "iconName": "UI_AvatarIcon_Xiangling",
        "costumes": {}
    },
    "10000024": {
        "iconName": "UI_AvatarIcon_Beidou",
        "costumes": {}
    },
    "10000025": {
        "iconName": "UI_AvatarIcon_Xingqiu",
        "costumes": {}
    },
    "10000026": {
        "iconName": "UI_AvatarIcon_Xiao",
        "costumes": {}
    },
    "10000027": {
        "iconName": "UI_AvatarIcon_Ningguang",
        "costumes": {
            "202701": {
                "iconName": "UI_AvatarIcon_NingguangCostumeFloral"
            }
        }
    },
    "10000029": {
        "iconName": "UI_AvatarIcon_Klee",
        "costumes": {}
    },
    "10000030": {
        "iconName": "UI_AvatarIcon_Zhongli",
        "costumes": {}
    },
    "10000031": {
        "iconName": "UI_AvatarIcon_Fischl",
        "costumes": {}
    },
    "10000032": {
        "iconName": "UI_AvatarIcon_Bennett",
        "costumes": {}
    },
    "10000033": {
        "iconName": "UI_AvatarIcon_Tartaglia",
        "costumes": {}
    },
    "10000034": {
        "iconName": "UI_AvatarIcon_Noel",
        "costumes": {}
    },
    "10000035": {
        "iconName": "UI_AvatarIcon_Qiqi",
        "costumes": {}
    },
    "10000036": {
        "iconName": "UI_AvatarIcon_Chongyun",
        "costumes": {}
    },
    "10000037": {
        "iconName": "UI_AvatarIcon_Ganyu",
        "costumes": {}
    },
    "10000038": {
        "iconName": "UI_AvatarIcon_Albedo",
        "costumes": {}
    },
    "10000039": {
        "iconName": "UI_AvatarIcon_Diona",
        "costumes": {}
    },
    "10000041": {
        "iconName": "UI_AvatarIcon_Mona",
        "costumes": {
            "204101": {
                "iconName": "UI_AvatarIcon_MonaCostumeWic"
            }
        }
    },
    "10000042": {
        "iconName": "UI_AvatarIcon_Keqing",
        "costumes": {
            "204201": {
                "iconName": "UI_AvatarIcon_KeqingCostumeFeather"
            }
        }
    },
    "10000043": {
        "iconName": "UI_AvatarIcon_Sucrose",
        "costumes": {}
    },
    "10000044": {
        "iconName": "UI_AvatarIcon_Xinyan",
        "costumes": {}
    },
    "10000045": {
        "iconName": "UI_AvatarIcon_Rosaria",
        "costumes": {
            "204501": {
                "iconName": "UI_AvatarIcon_RosariaCostumeWic"
            }
        }
    },
    "10000046": {
        "iconName": "UI_AvatarIcon_Hutao",
        "costumes": {}
    },
    "10000047": {
        "iconName": "UI_AvatarIcon_Kazuha",
        "costumes": {}
    },
    "10000048": {
        "iconName": "UI_AvatarIcon_Feiyan",
        "costumes": {}
    },
    "10000049": {
        "iconName": "UI_AvatarIcon_Yoimiya",
        "costumes": {}
    },
    "10000050": {
        "iconName": "UI_AvatarIcon_Tohma",
        "costumes": {}
    },
    "10000051": {
        "iconName": "UI_AvatarIcon_Eula",
        "costumes": {}
    },
    "10000052": {
        "iconName": "UI_AvatarIcon_Shougun",
        "costumes": {}
    },
    "10000053": {
        "iconName": "UI_AvatarIcon_Sayu",
        "costumes": {}
    },
    "10000054": {
        "iconName": "UI_AvatarIcon_Kokomi",
        "costumes": {}
    },
    "10000055": {
        "iconName": "UI_AvatarIcon_Gorou",
        "costumes": {}
    },
    "10000056": {
        "iconName": "UI_AvatarIcon_Sara",
        "costumes": {}
    },
    "10000057": {
        "iconName": "UI_AvatarIcon_Itto",
        "costumes": {}
    },
    "10000058": {
        "iconName": "UI_AvatarIcon_Yae",
        "costumes": {}
    },
    "10000060": {
        "iconName": "UI_AvatarIcon_Yelan",
        "costumes": {}
    },
    "10000062": {
        "iconName": "UI_AvatarIcon_Aloy",
        "costumes": {}
    },
    "10000063": {
        "iconName": "UI_AvatarIcon_Shenhe",
        "costumes": {}
    },
    "10000064": {
        "iconName": "UI_AvatarIcon_Yunjin",
        "costumes": {}
    },
    "10000065": {
        "iconName": "UI_AvatarIcon_Shinobu",
        "costumes": {}
    },
    "10000066": {
        "iconName": "UI_AvatarIcon_Ayato",
        "costumes": {}
    }
}